{
  "proofId": "proof:apps-platform-api-scripts-observability-control-route-runtime-proof-ts",
  "subjectType": "runtime-proof",
  "subjectIds": [
    "apps/platform-api/scripts/observability-control-route-runtime-proof.ts",
    "package.json#proof:observability-control-route",
    "proof:observability-control-route"
  ],
  "subjectId": "apps/platform-api/scripts/observability-control-route-runtime-proof.ts",
  "capabilityId": "capability:observability-control-route",
  "providerId": "not-applicable",
  "routeIds": [],
  "workflowIds": [],
  "eventIds": [],
  "storageIds": [],
  "environmentMode": "test",
  "providerMode": "compose-local",
  "proofLevelClaimed": "L0",
  "commandExecuted": "npm run proof:observability-control-route",
  "startedAt": "2026-06-23T08:53:16.445Z",
  "endedAt": "2026-06-23T08:53:16.962Z",
  "exitStatus": 0,
  "commit": "7b85515e24db3fa66d562d7f792853e2eb11f8bf",
  "realImplementationPathExecuted": "apps/platform-api/scripts/observability-control-route-runtime-proof.ts",
  "mockProviderUsed": false,
  "fakeProviderUsed": false,
  "inMemoryProviderUsed": false,
  "realLocalProviderUsed": false,
  "externalSandboxProviderUsed": false,
  "externalSandboxRequestIds": [],
  "beforeState": {},
  "afterState": {},
  "assertedStateDiff": {},
  "failurePathExercised": false,
  "sideEffectsAsserted": false,
  "tenantBoundaryAsserted": false,
  "securityBoundaryAsserted": false,
  "auditEventIds": [],
  "traceIds": [],
  "metricSamples": [],
  "logCorrelationIds": [],
  "cleanupResult": {
    "status": "not-emitted-by-proof"
  },
  "deterministicReplaySupported": false,
  "skipped": false,
  "skipReason": null,
  "generatedAt": "2026-06-23T08:53:16.962Z",
  "sourceFileRefs": ["apps/platform-api/scripts/observability-control-route-runtime-proof.ts"],
  "evidenceEmitter": "proof-process",
  "collectorRunId": "proof-run-1782204775248-2923776",
  "assertionsObserved": false,
  "expectedOutputsAsserted": false,
  "environment": "test",
  "proofLevelObserved": "L1",
  "startTime": "2026-06-23T08:53:16.445Z",
  "endTime": "2026-06-23T08:53:16.962Z",
  "gitCommit": "7b85515e24db3fa66d562d7f792853e2eb11f8bf",
  "executionTimestamp": "2026-06-23T08:53:16.962Z",
  "stateDiff": {},
  "failureMode": "not-exercised",
  "auditIds": [],
  "metricEvidence": [],
  "logEvidence": [],
  "evidenceSignature": "e555c52698478ae2e7808800d320df300e69ae35db85ba3314c5145264bca0d4"
}
