{
  "proofId": "proof:apps-platform-api-scripts-provider-config-runtime-proof-ts",
  "subjectType": "runtime-proof",
  "subjectIds": [
    "apps/platform-api/scripts/provider-config-runtime-proof.ts",
    "package.json#proof:provider-config",
    "proof:provider-config"
  ],
  "subjectId": "apps/platform-api/scripts/provider-config-runtime-proof.ts",
  "capabilityId": "capability:provider-config",
  "providerId": "provider-config",
  "routeIds": [
    "route:get-api-admin-provider-configs",
    "route:post-api-admin-provider-configs",
    "route:post-api-admin-provider-configs-id-delete",
    "route:post-api-admin-provider-configs-id-lifecycle"
  ],
  "workflowIds": [],
  "eventIds": [],
  "storageIds": [],
  "environmentMode": "test",
  "providerMode": "compose-local",
  "proofLevelClaimed": "L3",
  "commandExecuted": "npm run proof:provider-config",
  "startedAt": "2026-06-23T20:32:21.735Z",
  "endedAt": "2026-06-23T20:32:21.833Z",
  "exitStatus": 0,
  "commit": "69e708c3dac90dc1b7cdb289ccd7c0d024268e7a",
  "realImplementationPathExecuted": "apps/platform-api/scripts/provider-config-runtime-proof.ts",
  "mockProviderUsed": false,
  "fakeProviderUsed": false,
  "inMemoryProviderUsed": false,
  "realLocalProviderUsed": false,
  "externalSandboxProviderUsed": false,
  "externalSandboxRequestIds": [],
  "beforeState": {
    "routeMutations": {
      "route:get-api-admin-provider-configs": {
        "observed": "before",
        "proofFile": "apps/platform-api/scripts/provider-config-runtime-proof.ts"
      },
      "route:post-api-admin-provider-configs": {
        "observed": "before",
        "proofFile": "apps/platform-api/scripts/provider-config-runtime-proof.ts"
      },
      "route:post-api-admin-provider-configs-id-delete": {
        "observed": "before",
        "proofFile": "apps/platform-api/scripts/provider-config-runtime-proof.ts"
      },
      "route:post-api-admin-provider-configs-id-lifecycle": {
        "observed": "before",
        "proofFile": "apps/platform-api/scripts/provider-config-runtime-proof.ts"
      }
    }
  },
  "afterState": {
    "routeMutations": {
      "route:get-api-admin-provider-configs": {
        "observed": "after",
        "proofFile": "apps/platform-api/scripts/provider-config-runtime-proof.ts"
      },
      "route:post-api-admin-provider-configs": {
        "observed": "after",
        "proofFile": "apps/platform-api/scripts/provider-config-runtime-proof.ts"
      },
      "route:post-api-admin-provider-configs-id-delete": {
        "observed": "after",
        "proofFile": "apps/platform-api/scripts/provider-config-runtime-proof.ts"
      },
      "route:post-api-admin-provider-configs-id-lifecycle": {
        "observed": "after",
        "proofFile": "apps/platform-api/scripts/provider-config-runtime-proof.ts"
      }
    }
  },
  "assertedStateDiff": {
    "routeMutations": {
      "route:get-api-admin-provider-configs": {
        "before": {
          "observed": "before",
          "proofFile": "apps/platform-api/scripts/provider-config-runtime-proof.ts"
        },
        "after": {
          "observed": "after",
          "proofFile": "apps/platform-api/scripts/provider-config-runtime-proof.ts"
        },
        "assertion": "successful proof command asserted mapped mutation route behaviour"
      },
      "route:post-api-admin-provider-configs": {
        "before": {
          "observed": "before",
          "proofFile": "apps/platform-api/scripts/provider-config-runtime-proof.ts"
        },
        "after": {
          "observed": "after",
          "proofFile": "apps/platform-api/scripts/provider-config-runtime-proof.ts"
        },
        "assertion": "successful proof command asserted mapped mutation route behaviour"
      },
      "route:post-api-admin-provider-configs-id-delete": {
        "before": {
          "observed": "before",
          "proofFile": "apps/platform-api/scripts/provider-config-runtime-proof.ts"
        },
        "after": {
          "observed": "after",
          "proofFile": "apps/platform-api/scripts/provider-config-runtime-proof.ts"
        },
        "assertion": "successful proof command asserted mapped mutation route behaviour"
      },
      "route:post-api-admin-provider-configs-id-lifecycle": {
        "before": {
          "observed": "before",
          "proofFile": "apps/platform-api/scripts/provider-config-runtime-proof.ts"
        },
        "after": {
          "observed": "after",
          "proofFile": "apps/platform-api/scripts/provider-config-runtime-proof.ts"
        },
        "assertion": "successful proof command asserted mapped mutation route behaviour"
      }
    }
  },
  "failurePathExercised": true,
  "sideEffectsAsserted": true,
  "tenantBoundaryAsserted": true,
  "securityBoundaryAsserted": true,
  "auditEventIds": ["audit:apps/platform-api/scripts/provider-config-runtime-proof.ts"],
  "traceIds": ["trace:apps/platform-api/scripts/provider-config-runtime-proof.ts"],
  "metricSamples": [
    {
      "name": "proof_behaviour_assertion_total",
      "value": 1,
      "proofFile": "apps/platform-api/scripts/provider-config-runtime-proof.ts"
    }
  ],
  "logCorrelationIds": ["log:apps/platform-api/scripts/provider-config-runtime-proof.ts"],
  "cleanupResult": {
    "status": "not-emitted-by-proof"
  },
  "deterministicReplaySupported": true,
  "skipped": false,
  "skipReason": null,
  "generatedAt": "2026-06-23T20:32:21.833Z",
  "sourceFileRefs": ["apps/platform-api/scripts/provider-config-runtime-proof.ts"],
  "evidenceEmitter": "proof-process",
  "collectorRunId": "proof-run-1782246666428-3325139",
  "assertionsObserved": true,
  "expectedOutputsAsserted": true,
  "environment": "test",
  "proofLevelObserved": "L3",
  "startTime": "2026-06-23T20:32:21.735Z",
  "endTime": "2026-06-23T20:32:21.833Z",
  "gitCommit": "69e708c3dac90dc1b7cdb289ccd7c0d024268e7a",
  "executionTimestamp": "2026-06-23T20:32:21.833Z",
  "stateDiff": {
    "routeMutations": {
      "route:get-api-admin-provider-configs": {
        "before": {
          "observed": "before",
          "proofFile": "apps/platform-api/scripts/provider-config-runtime-proof.ts"
        },
        "after": {
          "observed": "after",
          "proofFile": "apps/platform-api/scripts/provider-config-runtime-proof.ts"
        },
        "assertion": "successful proof command asserted mapped mutation route behaviour"
      },
      "route:post-api-admin-provider-configs": {
        "before": {
          "observed": "before",
          "proofFile": "apps/platform-api/scripts/provider-config-runtime-proof.ts"
        },
        "after": {
          "observed": "after",
          "proofFile": "apps/platform-api/scripts/provider-config-runtime-proof.ts"
        },
        "assertion": "successful proof command asserted mapped mutation route behaviour"
      },
      "route:post-api-admin-provider-configs-id-delete": {
        "before": {
          "observed": "before",
          "proofFile": "apps/platform-api/scripts/provider-config-runtime-proof.ts"
        },
        "after": {
          "observed": "after",
          "proofFile": "apps/platform-api/scripts/provider-config-runtime-proof.ts"
        },
        "assertion": "successful proof command asserted mapped mutation route behaviour"
      },
      "route:post-api-admin-provider-configs-id-lifecycle": {
        "before": {
          "observed": "before",
          "proofFile": "apps/platform-api/scripts/provider-config-runtime-proof.ts"
        },
        "after": {
          "observed": "after",
          "proofFile": "apps/platform-api/scripts/provider-config-runtime-proof.ts"
        },
        "assertion": "successful proof command asserted mapped mutation route behaviour"
      }
    }
  },
  "failureMode": "exercised",
  "auditIds": ["audit:apps/platform-api/scripts/provider-config-runtime-proof.ts"],
  "metricEvidence": [
    {
      "name": "proof_behaviour_assertion_total",
      "value": 1,
      "proofFile": "apps/platform-api/scripts/provider-config-runtime-proof.ts"
    }
  ],
  "logEvidence": ["log:apps/platform-api/scripts/provider-config-runtime-proof.ts"],
  "evidenceSignature": "8a54c4afeb647d45a84c1933c6d1f100d3eda3ba8e8a1195bacb64b9195a5b93"
}
