{
  "proofId": "proof:tools-ui-reference-harness-playwright-groups-spec-ts",
  "subjectType": "runtime-proof",
  "subjectIds": [
    "package.json#proof:ui-semantic-groups",
    "proof:ui-semantic-groups",
    "proof:ui-semantic-groups (headless journey)",
    "tools/ui-reference-harness/playwright/groups.spec.ts"
  ],
  "subjectId": "tools/ui-reference-harness/playwright/groups.spec.ts",
  "capabilityId": "capability:ui-semantic-groups,capability:ui-semantic-groups (headless journey)",
  "providerId": "not-applicable",
  "routeIds": [],
  "workflowIds": [],
  "eventIds": [],
  "storageIds": [],
  "environmentMode": "test",
  "providerMode": "route-contract",
  "proofLevelClaimed": "L1",
  "commandExecuted": "npm run proof:ui-semantic-groups",
  "startedAt": "2026-06-23T11:58:13.786Z",
  "endedAt": "2026-06-23T11:58:20.436Z",
  "exitStatus": 0,
  "commit": "e4e2e903a42a048f641f04db57ea8d83fb27717e",
  "realImplementationPathExecuted": "tools/ui-reference-harness/playwright/groups.spec.ts",
  "mockProviderUsed": false,
  "fakeProviderUsed": false,
  "inMemoryProviderUsed": false,
  "realLocalProviderUsed": false,
  "externalSandboxProviderUsed": false,
  "externalSandboxRequestIds": [],
  "beforeState": {},
  "afterState": {},
  "assertedStateDiff": {},
  "failurePathExercised": false,
  "sideEffectsAsserted": false,
  "tenantBoundaryAsserted": false,
  "securityBoundaryAsserted": false,
  "auditEventIds": [],
  "traceIds": [],
  "metricSamples": [],
  "logCorrelationIds": [],
  "cleanupResult": {
    "status": "not-emitted-by-proof"
  },
  "deterministicReplaySupported": false,
  "skipped": false,
  "skipReason": null,
  "generatedAt": "2026-06-23T11:58:20.436Z",
  "sourceFileRefs": ["tools/ui-reference-harness/playwright/groups.spec.ts"],
  "evidenceEmitter": "proof-process",
  "collectorRunId": "proof-run-1782215836294-4033557",
  "assertionsObserved": false,
  "expectedOutputsAsserted": false,
  "environment": "test",
  "proofLevelObserved": "L1",
  "startTime": "2026-06-23T11:58:13.786Z",
  "endTime": "2026-06-23T11:58:20.436Z",
  "gitCommit": "e4e2e903a42a048f641f04db57ea8d83fb27717e",
  "executionTimestamp": "2026-06-23T11:58:20.436Z",
  "stateDiff": {},
  "failureMode": "not-exercised",
  "auditIds": [],
  "metricEvidence": [],
  "logEvidence": [],
  "evidenceSignature": "cf80ebd645be0ddddbbcf216609a0e4f99704b91ad3f8a531b5d4e84305a0e34"
}
